iribaker/__init__.py
iribaker-0.1.3.dist-info/METADATA
iribaker-0.1.3.dist-info/RECORD
iribaker-0.1.3.dist-info/WHEEL
iribaker-0.1.3.dist-info/top_level.txt
