Metadata-Version: 2.1
Name: iribaker
Version: 0.1.3
Summary: Safely convert IRI-like string to IRI.
Requires-Dist: rfc3987
